{
    "videos": [
        {
            "id": 1,
            "titulo": "NO OYES GRITAR LOS MUERTOS (RELATOS DE TERROR)",
            "capa": "https://i.ytimg.com/vi/c3AweP3Mxic/hq720.jpg?sqp=-oaymwEcCNAFEJQDSFXyq4qpAw4IARUAAIhCGAFwAcABBg==&rs=AOn4CLBUfcE1GLboc6_6jv1-BhL6BdAyDw",
            "link": "https://www.youtube.com/embed/c3AweP3Mxic"
        },
        {
            "id": 2,
            "titulo": "LA NOCHE DE LA SIRENA (HISTORIAS DE ENCUENTROS PARANORMALES)",
            "capa": "https://i.ytimg.com/vi/hbGJRbKJvBI/hq720.jpg?sqp=-oaymwEcCNAFEJQDSFXyq4qpAw4IARUAAIhCGAFwAcABBg==&rs=AOn4CLBXBkFl1INJG17C7-RkuT1G4WsmZA",
            "link": "https://www.youtube.com/embed/hbGJRbKJvBI"
        },
        {
            "id": 3,
            "titulo": "SUCESOS ATERRADORES EN CARRETERAS VOL. 2",
            "capa": "https://i.ytimg.com/vi/b5ZyBuZ0XSU/hq720.jpg?sqp=-oaymwEcCNAFEJQDSFXyq4qpAw4IARUAAIhCGAFwAcABBg==&rs=AOn4CLBp93P9QQJ2-a5UnoVeG-n4Dxl7Kw",
            "link": "https://www.youtube.com/embed/b5ZyBuZ0XSU"
        },
        {
            "id": 4,
            "titulo": "LA BRUJA DEL PEDREGAL DE SANTO DOMINGO",
            "capa": "https://i.ytimg.com/vi/tltfzZbb2OY/hq720.jpg?sqp=-oaymwEcCNAFEJQDSFXyq4qpAw4IARUAAIhCGAFwAcABBg==&rs=AOn4CLDOW4S5DSyXehnqJGaK9gyvsP5tIQ",
            "link": "https://www.youtube.com/embed/tltfzZbb2OY"
        },
        {
            "id": 5,
            "titulo": "NO DEJES QUE TE LLEVE EL MUERTO (Y MÁS RELATOS DE FANTASMAS)",
            "capa": "https://i.ytimg.com/vi/E6P-tpjWZE4/hq720.jpg?sqp=-oaymwEcCNAFEJQDSFXyq4qpAw4IARUAAIhCGAFwAcABBg==&rs=AOn4CLDOFNeoF3-A6uFCM02ASgdlEUIvPw",
            "link": "https://www.youtube.com/embed/E6P-tpjWZE4"
        },
        {
            "id": 6,
            "titulo": "LA LEYENDA DEL MANIQUÍ QUE CAMINA EN REFORMA",
            "capa": "https://i.ytimg.com/vi/KlE68HUswuE/hq720.jpg?sqp=-oaymwEcCNAFEJQDSFXyq4qpAw4IARUAAIhCGAFwAcABBg==&rs=AOn4CLAJhiGWojJmLoUPW68r6k-aCSK7RQ",
            "link": "https://www.youtube.com/embed/KlE68HUswuE"
        }
    ]
}